OMIEData/__init__.py
OMIEData/DataImport/__init__.py
OMIEData/DataImport/omie_adjustmentprice_importer.py
OMIEData/DataImport/omie_data_importer.py
OMIEData/DataImport/omie_data_importer_from_folder.py
OMIEData/DataImport/omie_data_importer_from_responses.py
OMIEData/DataImport/omie_energy_by_technology_importer.py
OMIEData/DataImport/omie_marginalprice_importer.py
OMIEData/DataImport/omie_supply_demand_curve_importer.py
OMIEData/Downloaders/__init__.py
OMIEData/Downloaders/adjustment_price_downloader.py
OMIEData/Downloaders/energy_by_technology_downloader.py
OMIEData/Downloaders/general_omie_downloader.py
OMIEData/Downloaders/intra_day_price_downloader.py
OMIEData/Downloaders/marginal_price_downloader.py
OMIEData/Downloaders/omie_downloader.py
OMIEData/Downloaders/supply_demand_curve_downloader.py
OMIEData/Enums/__init__.py
OMIEData/Enums/all_enums.py
OMIEData/FileReaders/__init__.py
OMIEData/FileReaders/adjustment_price_file_reader.py
OMIEData/FileReaders/data_types_energy_by_technology.py
OMIEData/FileReaders/data_types_marginal_price_file.py
OMIEData/FileReaders/energy_by_technology_files_reader.py
OMIEData/FileReaders/marginal_price_file_reader.py
OMIEData/FileReaders/omie_file_reader.py
OMIEData/FileReaders/supply_demand_curve_file_reader.py
omiedata-0.4.0.0.dist-info/licenses/LICENSE
tests/__init__.py
tests/filereaders_tests/__init__.py
tests/filereaders_tests/adjustment_price_reader_test.py
tests/filereaders_tests/energy_by_technology_reader_test.py
tests/filereaders_tests/marginal_pricer_reader_test.py
omiedata-0.4.0.0.dist-info/METADATA
omiedata-0.4.0.0.dist-info/WHEEL
omiedata-0.4.0.0.dist-info/top_level.txt
omiedata-0.4.0.0.dist-info/RECORD
