Metadata-Version: 2.4
Name: OMIEData
Version: 0.4.0.0
Summary: Package to download electricity time series from https://www.omie.es/
Home-page: https://github.com/acruzgarcia/OMIEData
Author: Alberto Cruz and Mirel Mora
Author-email: a.cruz.g arcia@gmail.com, mirel.mora@gmail.com
Keywords: OMIE,Electricity prices
Classifier: Programming Language :: Python :: 3
Classifier: License :: OSI Approved :: MIT License
Classifier: Operating System :: OS Independent
Requires-Python: >=3.10
License-File: LICENSE
Requires-Dist: pandas>=2.0.1
Requires-Dist: requests
Requires-Dist: datetime
Requires-Dist: babel
Dynamic: author
Dynamic: author-email
Dynamic: classifier
Dynamic: description
Dynamic: description-content-type
Dynamic: home-page
Dynamic: keywords
Dynamic: license-file
Dynamic: requires-dist
Dynamic: requires-python
Dynamic: summary
